twitter_unfollow_tool/__init__.py
twitter_unfollow_tool/extractor.py
twitter_unfollow_tool/scroll.py
twitter_unfollow_tool/unfollow.py
twitter_unfollow_tool-0.1.0.dist-info/licenses/LICENSE
twitter_unfollow_tool-0.1.0.dist-info/METADATA
twitter_unfollow_tool-0.1.0.dist-info/WHEEL
twitter_unfollow_tool-0.1.0.dist-info/top_level.txt
twitter_unfollow_tool-0.1.0.dist-info/RECORD
