Metadata-Version: 2.4
Name: twitter-unfollow-tool
Version: 0.1.0
Summary: Twitterの非相互フォローを検出・解除するPythonライブラリ
Author-email: fujitasan-create <blackokayu@yahoo.co.jp>
License: MIT
Project-URL: Homepage, https://github.com/yourname/twitter-unfollow-tool
Requires-Python: >=3.8
License-File: LICENSE
Requires-Dist: selenium>=4.0.0
Dynamic: license-file
